get_def.py
get_def-0.6.dist-info/METADATA
get_def-0.6.dist-info/WHEEL
get_def-0.6.dist-info/entry_points.txt
get_def-0.6.dist-info/licenses/LICENSE
get_def-0.6.dist-info/RECORD
